eventregpy/__init__.py
eventregpy/tools.py
eventregpy-1.0.2.dist-info/top_level.txt
eventregpy-1.0.2.dist-info/METADATA
eventregpy-1.0.2.dist-info/DESCRIPTION.rst
eventregpy-1.0.2.dist-info/metadata.json
eventregpy-1.0.2.dist-info/WHEEL
eventregpy-1.0.2.dist-info/RECORD
