Metadata-Version: 2.0
Name: eventregpy
Version: 1.0.2
Summary: An Events Registry
Home-page: https://github.com/phenicle/eventregpy
Author: Phenicle
Author-email: pheniclebeefheart@gmail.com
License: Mozilla Public License 2.0 (MPL 2.0)
Platform: UNKNOWN
Requires-Dist: cfgpy
Requires-Dist: psycopg2
